netteikei/__init__.py
netteikei/core.py
netteikei/py.typed
netteikei/typedefs.py
netteikei/contrib/__init__.py
netteikei/contrib/download.py
netteikei/contrib/utils.py
netteikei-0.4.2.dist-info/LICENSE
netteikei-0.4.2.dist-info/METADATA
netteikei-0.4.2.dist-info/WHEEL
netteikei-0.4.2.dist-info/top_level.txt
netteikei-0.4.2.dist-info/RECORD
