Metadata-Version: 2.1
Name: netteikei
Version: 0.4.2
Summary: Utility for making concurrent HTTP requests with aiohttp
Home-page: https://github.com/fernofsigma/netteikei
Author: FernOfSigma
Author-email: fernofsigma@tuta.io
License: MIT
Project-URL: GitHub: issues, https://github.com/fernofsigma/netteikei/issues
Project-URL: GitHub: repo, https://github.com/fernofsigma/netteikei
Classifier: Development Status :: 3 - Alpha
Classifier: Framework :: AsyncIO
Classifier: Intended Audience :: Developers
Classifier: License :: OSI Approved :: MIT License
Classifier: Operating System :: POSIX
Classifier: Operating System :: MacOS :: MacOS X
Classifier: Operating System :: Microsoft :: Windows
Classifier: Programming Language :: Python
Classifier: Programming Language :: Python :: 3
Classifier: Programming Language :: Python :: 3.11
Classifier: Programming Language :: Python :: 3.12
Classifier: Topic :: Internet :: WWW/HTTP
Classifier: Topic :: Software Development :: Libraries
Classifier: Topic :: Utilities
Classifier: Typing :: Typed
Requires-Python: >=3.11
License-File: LICENSE
Requires-Dist: aiohttp (<4.0.0,>=3.8.4)
Provides-Extra: download
Requires-Dist: aiofiles ; extra == 'download'
Requires-Dist: pyrfc6266 ; extra == 'download'
Requires-Dist: tqdm ; extra == 'download'
Provides-Extra: speedups
Requires-Dist: aiohttp[speedups] ; extra == 'speedups'
